napari_locan/__init__.py
napari_locan/_scripts.py
napari_locan/_version.py
napari_locan/napari.yaml
napari_locan/data_model/__init__.py
napari_locan/data_model/data_model_base.py
napari_locan/data_model/filter_specifications.py
napari_locan/data_model/region_specifications.py
napari_locan/data_model/roi_specifications.py
napari_locan/data_model/smlm_data.py
napari_locan/sample_data/__init__.py
napari_locan/sample_data/sample_data.py
napari_locan/scripts/__init__.py
napari_locan/scripts/npc_gp210.asdf
napari_locan/scripts/script_hello.py
napari_locan/scripts/script_load.py
napari_locan/tests/__init__.py
napari_locan/tests/test_import.py
napari_locan/widgets/__init__.py
napari_locan/widgets/widget_clustering.py
napari_locan/widgets/widget_filter_specifications.py
napari_locan/widgets/widget_io_save.py
napari_locan/widgets/widget_load.py
napari_locan/widgets/widget_napari_locan_project.py
napari_locan/widgets/widget_property_distribution.py
napari_locan/widgets/widget_render_collection_2d.py
napari_locan/widgets/widget_render_collection_features.py
napari_locan/widgets/widget_render_features.py
napari_locan/widgets/widget_render_image_2d.py
napari_locan/widgets/widget_render_image_3d.py
napari_locan/widgets/widget_render_points_2d.py
napari_locan/widgets/widget_render_points_3d.py
napari_locan/widgets/widget_roi.py
napari_locan/widgets/widget_run_script.py
napari_locan/widgets/widget_select.py
napari_locan/widgets/widget_show_data.py
napari_locan/widgets/widget_show_info.py
napari_locan/widgets/widget_show_metadata.py
napari_locan/widgets/widget_show_properties.py
napari_locan/widgets/widget_smlm_data.py
napari_locan-0.7.0.dist-info/LICENSE.md
napari_locan-0.7.0.dist-info/METADATA
napari_locan-0.7.0.dist-info/WHEEL
napari_locan-0.7.0.dist-info/entry_points.txt
napari_locan-0.7.0.dist-info/top_level.txt
napari_locan-0.7.0.dist-info/RECORD
