Metadata-Version: 2.2
Name: napari-locan
Version: 0.7.0
Summary: Use locan methods in napari for single-molecule localization microscopy data.
Author: napari-locan Developers
Maintainer: Sören Doose
License: BSD 3-Clause License
Project-URL: homepage, https://github.com/super-resolution/napari-locan
Project-URL: documentation, https://napari-locan.readthedocs.io/
Project-URL: issues, https://github.com/super-resolution/napari-locan/issues
Project-URL: discussions, https://github.com/super-resolution/napari-locan/discussions
Project-URL: changelog, https://github.com/super-resolution/napari-locan/CHANGES.rst
Project-URL: Source Code, https://github.com/super-resolution/napari-locan
Project-URL: Bug Tracker, https://github.com/super-resolution/napari-locan/issues
Project-URL: User Support, https://github.com/super-resolution/napari-locan/discussions
Keywords: napari plugin,locan
Classifier: Development Status :: 3 - Alpha
Classifier: Environment :: X11 Applications :: Qt
Classifier: Framework :: napari
Classifier: Intended Audience :: Education
Classifier: Intended Audience :: Science/Research
Classifier: License :: OSI Approved :: BSD License
Classifier: Operating System :: MacOS
Classifier: Operating System :: Microsoft :: Windows
Classifier: Operating System :: POSIX
Classifier: Operating System :: Unix
Classifier: Programming Language :: Python
Classifier: Programming Language :: Python :: 3
Classifier: Programming Language :: Python :: 3.9
Classifier: Programming Language :: Python :: 3.10
Classifier: Programming Language :: Python :: 3.11
Classifier: Programming Language :: Python :: 3.12
Classifier: Topic :: Scientific/Engineering
Classifier: Topic :: Scientific/Engineering :: Bio-Informatics
Classifier: Topic :: Scientific/Engineering :: Image Processing
Classifier: Topic :: Scientific/Engineering :: Information Analysis
Classifier: Topic :: Scientific/Engineering :: Visualization
Requires-Python: >=3.9
License-File: LICENSE.md
Requires-Dist: locan>=0.18
Requires-Dist: matplotlib
Requires-Dist: napari
Requires-Dist: napari-matplotlib
Requires-Dist: numpy
Requires-Dist: qtpy
Provides-Extra: test
Requires-Dist: locan[http]>=0.18; extra == "test"
Requires-Dist: pytest; extra == "test"
Requires-Dist: pytest-qt; extra == "test"
Provides-Extra: dev
Requires-Dist: black~=25.0; extra == "dev"
Requires-Dist: build; extra == "dev"
Requires-Dist: coverage[toml]; extra == "dev"
Requires-Dist: mypy; extra == "dev"
Requires-Dist: pandas-stubs; extra == "dev"
Requires-Dist: pre-commit; extra == "dev"
Requires-Dist: ruff; extra == "dev"
Requires-Dist: twine; extra == "dev"
Provides-Extra: docs
Requires-Dist: furo; extra == "docs"
Requires-Dist: ipython; extra == "docs"
Requires-Dist: myst-nb; extra == "docs"
Requires-Dist: napari>=0.4.17; extra == "docs"
Requires-Dist: sphinx; extra == "docs"
Requires-Dist: sphinx-autodoc-typehints; extra == "docs"
Requires-Dist: sphinx-copybutton; extra == "docs"
